setup.py
aicloud_test.egg-info/PKG-INFO
aicloud_test.egg-info/SOURCES.txt
aicloud_test.egg-info/dependency_links.txt
aicloud_test.egg-info/requires.txt
aicloud_test.egg-info/top_level.txt
debug/__init__.py
debug/print_str.py