Metadata-Version: 1.2
Name: aicloud-test
Version: 0.0.1
Summary: PyPI Tutorial
Home-page: UNKNOWN
Author: liyichao
Author-email: 728509423@example.com
License: UNKNOWN
Platform: UNKNOWN
Classifier: Programming Language :: Python :: 3
Classifier: License :: OSI Approved :: MIT License
Classifier: Operating System :: OS Independent
Requires-Python: >=3
